{
	"items": [
		{
			"_id": "5c6687d65e9d882c8841f0fd",
			"_tpl": "55d7217a4bdc2d86028b456d"
		},
		{
			"_id": "5c6687d65e9d882c8841f121",
			"_tpl": "557ffd194bdc2d28148b457f",
			"parentId": "5c6687d65e9d882c8841f0fd",
			"slotId": "Pockets"
		},
		{
			"_id": "5c6687d65e9d882c8841f0fc",
			"_tpl": "566abbc34bdc2d92178b4576"
		},
		{
			"_id": "5c6687d65e9d882c8841f0ff",
			"_tpl": "5963866b86f7747bfa1c4462"
		},
		{
			"_id": "5c6687d65e9d882c8841f0fe",
			"_tpl": "5963866286f7747bf429b572"
		},
		{
			"_id": "TacticalVest470821",
			"_tpl": "5b44cad286f77402a54ae7e5",
			"parentId": "5c6687d65e9d882c8841f0fd",
			"slotId": "TacticalVest",
			"upd": {
				"SpawnedInSession": true
			}
		},
		{
			"_id": "I07236512524719139pkwSI5",
			"_tpl": "59984ab886f7743e98271174",
			"parentId": "5c6687d65e9d882c8841f0fd",
			"slotId": "FirstPrimaryWeapon"
		},
		{
			"_id": "I07236514144869147SgQs0j",
			"_tpl": "5cf50850d7f00c056e24104c",
			"parentId": "I07236512524719139pkwSI5",
			"slotId": "mod_pistol_grip",
			"upd": {
				"SpawnedInSession": true
			}
		},
		{
			"_id": "I07236511680412429IeI0jj",
			"_tpl": "5cf50fc5d7f00c056c53f83c",
			"parentId": "I07236512524719139pkwSI5",
			"slotId": "mod_stock",
			"upd": {
				"SpawnedInSession": true
			}
		},
		{
			"_id": "I07236514862348189htM48u",
			"_tpl": "5648ac824bdc2ded0b8b457d",
			"parentId": "I07236512524719139pkwSI5",
			"slotId": "mod_charge",
			"upd": {
				"SpawnedInSession": true
			}
		},
		{
			"_id": "MagazineWeaponScav6664",
			"_tpl": "5c0673fb0db8340023300271",
			"parentId": "I07236512524719139pkwSI5",
			"slotId": "mod_magazine"
		},
		{
			"_id": "AmmoMag18343",
			"_tpl": "5c3df7d588a4501f290594e5",
			"parentId": "MagazineWeaponScav6664",
			"slotId": "cartridges",
			"upd": {
				"StackObjectsCount": 20
			}
		},
		{
			"_id": "I07236519151853991lE9WrI",
			"_tpl": "5998598e86f7740b3f498a86",
			"parentId": "I07236512524719139pkwSI5",
			"slotId": "mod_muzzle",
			"upd": {
				"SpawnedInSession": true
			}
		},
		{
			"_id": "I07236516341727642kF7Urk",
			"_tpl": "59985a8086f77414ec448d1a",
			"parentId": "I07236512524719139pkwSI5",
			"slotId": "mod_reciever",
			"upd": {
				"SpawnedInSession": true
			}
		},
		{
			"_id": "I07236514194650943GhXgvb",
			"_tpl": "599860e986f7743bb57573a6",
			"parentId": "I07236512524719139pkwSI5",
			"slotId": "mod_sight_rear",
			"upd": {
				"SpawnedInSession": true
			}
		},
		{
			"_id": "I07236514640260636FNoCSX",
			"_tpl": "57acb6222459771ec34b5cb0",
			"parentId": "I07236512524719139pkwSI5",
			"slotId": "mod_scope",
			"upd": {
				"SpawnedInSession": true
			}
		},
		{
			"_id": "I072365161607198418SsESc",
			"_tpl": "59ccd11386f77428f24a488f",
			"parentId": "I07236512524719139pkwSI5",
			"slotId": "mod_gas_block",
			"upd": {
				"SpawnedInSession": true
			}
		},
		{
			"_id": "I07236513034189472aLVPxq",
			"_tpl": "5bfe86df0db834001b734685",
			"parentId": "I07236511680412429IeI0jj",
			"slotId": "mod_stock",
			"upd": {
				"SpawnedInSession": true
			}
		},
		{
			"_id": "I07236519700911750h8N1bk",
			"_tpl": "570fd79bd2720bc7458b4583",
			"parentId": "I07236514640260636FNoCSX",
			"slotId": "mod_scope",
			"upd": {
				"SpawnedInSession": true
			}
		},
		{
			"_id": "I07236512028134682AGPZJx",
			"_tpl": "57cffe20245977632f391a9d",
			"parentId": "I072365161607198418SsESc",
			"slotId": "mod_handguard",
			"upd": {
				"SpawnedInSession": true
			}
		},
		{
			"_id": "I07236512540930985rXHAMe",
			"_tpl": "5b7be4895acfc400170e2dd5",
			"parentId": "I07236512028134682AGPZJx",
			"slotId": "mod_mount_003",
			"upd": {
				"SpawnedInSession": true
			}
		},
		{
			"_id": "I07236513483409109zLmO49",
			"_tpl": "58c157c886f774032749fb06",
			"parentId": "I07236512540930985rXHAMe",
			"slotId": "mod_foregrip",
			"upd": {
				"SpawnedInSession": true
			}
		},
		{
			"_id": "mag4Vest139381",
			"_tpl": "5998529a86f774647f44f421",
			"parentId": "TacticalVest470821",
			"slotId": "9",
			"location": {
				"x": 0,
				"y": 0,
				"r": "Horizontal"
			}
		},
		{
			"_id": "AmmoMag4Vest183059",
			"_tpl": "5a3c16fe86f77452b62de32a",
			"parentId": "mag4Vest139381",
			"slotId": "cartridges",
			"upd": {
				"StackObjectsCount": 10
			}
		},
		{
			"_id": "Scabbard835806",
			"_tpl": "57e26ea924597715ca604a09",
			"parentId": "5c6687d65e9d882c8841f0fd",
			"slotId": "Scabbard",
			"upd": {
				"SpawnedInSession": true
			}
		},
		{
			"_id": "Eyewear152468",
			"_tpl": "5d6d2ef3a4b93618084f58bd",
			"parentId": "5c6687d65e9d882c8841f0fd",
			"slotId": "Eyewear",
			"upd": {
				"SpawnedInSession": true
			}
		},
		{
			"_id": "FaceCover618117",
			"_tpl": "5b4326435acfc433000ed01d",
			"parentId": "5c6687d65e9d882c8841f0fd",
			"slotId": "FaceCover",
			"upd": {
				"SpawnedInSession": true
			}
		},
		{
			"_id": "Backpack96020",
			"_tpl": "5b44c6ae86f7742d1627baea",
			"parentId": "5c6687d65e9d882c8841f0fd",
			"slotId": "Backpack",
			"upd": {
				"SpawnedInSession": true
			}
		},
		{
			"_id": "BP_Backpack96020_197452",
			"_tpl": "5c9a1c3a2e2216000e69fb6a",
			"parentId": "Backpack96020",
			"slotId": "main",
			"location": {
				"x": 0,
				"y": 0,
				"r": "Horizontal"
			},
			"upd": {
				"SpawnedInSession": true
			}
		},
		{
			"_id": "BP_Backpack96020_606746",
			"_tpl": "588b56d02459771481110ae2",
			"parentId": "Backpack96020",
			"slotId": "main",
			"location": {
				"x": 0,
				"y": 1,
				"r": "Horizontal"
			},
			"upd": {
				"SpawnedInSession": true
			}
		},
		{
			"_id": "BP_Backpack96020_942021",
			"_tpl": "5c0695860db834001b735461",
			"parentId": "Backpack96020",
			"slotId": "main",
			"location": {
				"x": 0,
				"y": 2,
				"r": "Horizontal"
			},
			"upd": {
				"SpawnedInSession": true
			}
		},
		{
			"_id": "BP_Backpack96020_604066",
			"_tpl": "5c5db5852e2216003a0fe71a",
			"parentId": "Backpack96020",
			"slotId": "main",
			"location": {
				"x": 0,
				"y": 3,
				"r": "Horizontal"
			},
			"upd": {
				"SpawnedInSession": true
			}
		},
		{
			"_id": "BP_Backpack96020_490220",
			"_tpl": "58272b392459774b4c7b3ccd",
			"parentId": "Backpack96020",
			"slotId": "main",
			"location": {
				"x": 0,
				"y": 4,
				"r": "Horizontal"
			},
			"upd": {
				"SpawnedInSession": true
			}
		},
		{
			"_id": "BP_Backpack96020_781558",
			"_tpl": "5df35e59c41b2312ea3334d5",
			"parentId": "Backpack96020",
			"slotId": "main",
			"location": {
				"x": 0,
				"y": 5,
				"r": "Horizontal"
			},
			"upd": {
				"SpawnedInSession": true
			}
		},
		{
			"_id": "BP_Backpack96020_375983",
			"_tpl": "5d25d0ac8abbc3054f3e61f7",
			"parentId": "Backpack96020",
			"slotId": "main",
			"location": {
				"x": 1,
				"y": 2,
				"r": "Horizontal"
			},
			"upd": {
				"SpawnedInSession": true
			}
		},
		{
			"_id": "BP_Backpack96020_992318",
			"_tpl": "5926c32286f774616e42de99",
			"parentId": "Backpack96020",
			"slotId": "main",
			"location": {
				"x": 1,
				"y": 3,
				"r": "Horizontal"
			},
			"upd": {
				"SpawnedInSession": true
			}
		},
		{
			"_id": "BP_Backpack96020_839224",
			"_tpl": "5bb20de5d4351e0035629e59",
			"parentId": "Backpack96020",
			"slotId": "main",
			"location": {
				"x": 2,
				"y": 0,
				"r": "Horizontal"
			},
			"upd": {
				"SpawnedInSession": true
			}
		},
		{
			"_id": "BP_Backpack96020_839002",
			"_tpl": "5cde739cd7f00c0010373bd3",
			"parentId": "Backpack96020",
			"slotId": "main",
			"location": {
				"x": 2,
				"y": 1,
				"r": "Horizontal"
			},
			"upd": {
				"SpawnedInSession": true
			}
		},
		{
			"_id": "BP_Backpack96020_852442",
			"_tpl": "5c4eecde2e221602b3140418",
			"parentId": "Backpack96020",
			"slotId": "main",
			"location": {
				"x": 2,
				"y": 3,
				"r": "Horizontal"
			},
			"upd": {
				"SpawnedInSession": true
			}
		},
		{
			"_id": "BP_Backpack96020_820098",
			"_tpl": "5c0e2f5cd174af02a012cfc9",
			"parentId": "Backpack96020",
			"slotId": "main",
			"location": {
				"x": 2,
				"y": 4,
				"r": "Horizontal"
			},
			"upd": {
				"SpawnedInSession": true
			}
		},
		{
			"_id": "BP_Backpack96020_601996",
			"_tpl": "5839a7742459773cf9693481",
			"parentId": "Backpack96020",
			"slotId": "main",
			"location": {
				"x": 2,
				"y": 5,
				"r": "Horizontal"
			},
			"upd": {
				"SpawnedInSession": true
			}
		},
		{
			"_id": "BP_Backpack96020_765943",
			"_tpl": "5c0006470db834001a6697fe",
			"parentId": "Backpack96020",
			"slotId": "main",
			"location": {
				"x": 3,
				"y": 3,
				"r": "Horizontal"
			},
			"upd": {
				"SpawnedInSession": true
			}
		},
		{
			"_id": "ArmorVest593503",
			"_tpl": "5ab8e79e86f7742d8b372e78",
			"parentId": "5c6687d65e9d882c8841f0fd",
			"slotId": "ArmorVest",
			"upd": {
				"Repairable": {
					"MaxDurability": 75,
					"Durability": 8
				}
			}
		},
		{
			"_id": "Pocket_182371",
			"_tpl": "5af04e0a86f7743a532b79e2",
			"parentId": "5c6687d65e9d882c8841f121",
			"slotId": "pocket1",
			"location": {
				"x": 0,
				"y": 0,
				"r": "Horizontal"
			},
			"upd": {
				"SpawnedInSession": true
			}
		}
	],
	"equipment": "5c6687d65e9d882c8841f0fd",
	"stash": "5c6687d65e9d882c8841f0fc",
	"questRaidItems": "5c6687d65e9d882c8841f0fe",
	"questStashItems": "5c6687d65e9d882c8841f0ff",
	"fastPanel": {}
}