{
	"items": [
		{
			"_id": "5c6687d65e9d882c8841f0fd",
			"_tpl": "55d7217a4bdc2d86028b456d"
		},
		{
			"_id": "5c6687d65e9d882c8841f121",
			"_tpl": "557ffd194bdc2d28148b457f",
			"parentId": "5c6687d65e9d882c8841f0fd",
			"slotId": "Pockets"
		},
		{
			"_id": "5c6687d65e9d882c8841f0fc",
			"_tpl": "566abbc34bdc2d92178b4576"
		},
		{
			"_id": "5c6687d65e9d882c8841f0ff",
			"_tpl": "5963866b86f7747bfa1c4462"
		},
		{
			"_id": "5c6687d65e9d882c8841f0fe",
			"_tpl": "5963866286f7747bf429b572"
		},
		{
			"_id": "TacticalVest179037",
			"_tpl": "5648a69d4bdc2ded0b8b457b",
			"parentId": "5c6687d65e9d882c8841f0fd",
			"slotId": "TacticalVest",
			"upd": {
				"SpawnedInSession": true
			}
		},
		{
			"_id": "5b439b7486f7744fd8059cd8",
			"_tpl": "574d967124597745970e7c94",
			"parentId": "5c6687d65e9d882c8841f0fd",
			"slotId": "FirstPrimaryWeapon"
		},
		{
			"_id": "5b439b7486f7744fd8059cd9",
			"_tpl": "5afd7ded5acfc40017541f5e",
			"parentId": "5b439b7486f7744fd8059cd8",
			"slotId": "mod_stock",
			"upd": {
				"SpawnedInSession": true
			}
		},
		{
			"_id": "5b439b7486f7744fd8059cda",
			"_tpl": "5afd7e095acfc40017541f61",
			"parentId": "5b439b7486f7744fd8059cd9",
			"slotId": "mod_stock",
			"upd": {
				"SpawnedInSession": true
			}
		},
		{
			"_id": "5b439b7486f7744fd8059cdb",
			"_tpl": "55d4ae6c4bdc2d8b2f8b456e",
			"parentId": "5b439b7486f7744fd8059cda",
			"slotId": "mod_stock",
			"upd": {
				"SpawnedInSession": true
			}
		},
		{
			"_id": "5b439b7486f7744fd8059cdc",
			"_tpl": "5afd7e445acfc4001637e35a",
			"parentId": "5b439b7486f7744fd8059cd9",
			"slotId": "mod_pistol_grip",
			"upd": {
				"SpawnedInSession": true
			}
		},
		{
			"_id": "5b439b7486f7744fd8059cdd",
			"_tpl": "574db213245977459a2f3f5d",
			"parentId": "5b439b7486f7744fd8059cd8",
			"slotId": "mod_sight_rear",
			"upd": {
				"SpawnedInSession": true
			}
		},
		{
			"_id": "MagazineWeaponScav5586",
			"_tpl": "587df3a12459772c28142567",
			"parentId": "5b439b7486f7744fd8059cd8",
			"slotId": "mod_magazine",
			"upd": {
				"SpawnedInSession": true
			}
		},
		{
			"_id": "AmmoMag14965",
			"_tpl": "59e4d24686f7741776641ac7",
			"parentId": "MagazineWeaponScav5586",
			"slotId": "cartridges",
			"upd": {
				"SpawnedInSession": true,
				"StackObjectsCount": 10
			}
		},
		{
			"_id": "mag1Vest572577",
			"_tpl": "587df3a12459772c28142567",
			"parentId": "TacticalVest179037",
			"slotId": "2",
			"location": {
				"x": 0,
				"y": 0,
				"r": "Horizontal"
			},
			"upd": {
				"SpawnedInSession": true
			}
		},
		{
			"_id": "AmmoMag1Vest781888",
			"_tpl": "59e4cf5286f7741778269d8a",
			"parentId": "mag1Vest572577",
			"slotId": "cartridges",
			"upd": {
				"SpawnedInSession": true,
				"StackObjectsCount": 10
			}
		},
		{
			"_id": "mag4Vest349750",
			"_tpl": "587df3a12459772c28142567",
			"parentId": "TacticalVest179037",
			"slotId": "11",
			"location": {
				"x": 0,
				"y": 0,
				"r": "Horizontal"
			},
			"upd": {
				"SpawnedInSession": true
			}
		},
		{
			"_id": "AmmoMag4Vest345317",
			"_tpl": "5656d7c34bdc2d9d198b4587",
			"parentId": "mag4Vest349750",
			"slotId": "cartridges",
			"upd": {
				"SpawnedInSession": true,
				"StackObjectsCount": 10
			}
		},
		{
			"_id": "mag4Vest346963",
			"_tpl": "587df3a12459772c28142567",
			"parentId": "TacticalVest179037",
			"slotId": "11",
			"location": {
				"x": 0,
				"y": 1,
				"r": "Horizontal"
			},
			"upd": {
				"SpawnedInSession": true
			}
		},
		{
			"_id": "AmmoMag4Vest653185",
			"_tpl": "5656d7c34bdc2d9d198b4587",
			"parentId": "mag4Vest346963",
			"slotId": "cartridges",
			"upd": {
				"SpawnedInSession": true,
				"StackObjectsCount": 10
			}
		},
		{
			"_id": "StackAmmo31892469741",
			"_tpl": "5656d7c34bdc2d9d198b4587",
			"parentId": "TacticalVest179037",
			"slotId": "6",
			"upd": {
				"SpawnedInSession": true,
				"StackObjectsCount": 23
			}
		},
		{
			"_id": "StackAmmo52095153003",
			"_tpl": "59e4d24686f7741776641ac7",
			"parentId": "TacticalVest179037",
			"slotId": "9",
			"upd": {
				"SpawnedInSession": true,
				"StackObjectsCount": 27
			}
		},
		{
			"_id": "Scabbard124325",
			"_tpl": "57e26fc7245977162a14b800",
			"parentId": "5c6687d65e9d882c8841f0fd",
			"slotId": "Scabbard",
			"upd": {
				"SpawnedInSession": true
			}
		},
		{
			"_id": "FaceCover435710",
			"_tpl": "572b7f1624597762ae139822",
			"parentId": "5c6687d65e9d882c8841f0fd",
			"slotId": "FaceCover",
			"upd": {
				"SpawnedInSession": true
			}
		},
		{
			"_id": "Backpack67007",
			"_tpl": "5ab8f04f86f774585f4237d8",
			"parentId": "5c6687d65e9d882c8841f0fd",
			"slotId": "Backpack",
			"upd": {
				"SpawnedInSession": true
			}
		},
		{
			"_id": "BP_Backpack67007_551124",
			"_tpl": "578395e82459774a0e553c7b",
			"parentId": "Backpack67007",
			"slotId": "main",
			"location": {
				"x": 0,
				"y": 0,
				"r": "Horizontal"
			},
			"upd": {
				"SpawnedInSession": true
			}
		},
		{
			"_id": "BP_Backpack67007_434180",
			"_tpl": "5648ae314bdc2d3d1c8b457f",
			"parentId": "Backpack67007",
			"slotId": "main",
			"location": {
				"x": 0,
				"y": 1,
				"r": "Horizontal"
			},
			"upd": {
				"SpawnedInSession": true
			}
		},
		{
			"_id": "ArmorVest218824",
			"_tpl": "59e7635f86f7742cbf2c1095",
			"parentId": "5c6687d65e9d882c8841f0fd",
			"slotId": "ArmorVest",
			"upd": {
				"Repairable": {
					"MaxDurability": 40,
					"Durability": 10
				}
			}
		},
		{
			"_id": "Pocket_339624",
			"_tpl": "5734779624597737e04bf329",
			"parentId": "5c6687d65e9d882c8841f121",
			"slotId": "pocket1",
			"location": {
				"x": 0,
				"y": 0,
				"r": "Horizontal"
			},
			"upd": {
				"SpawnedInSession": true
			}
		},
		{
			"_id": "Pocket_682534",
			"_tpl": "59faf7ca86f7740dbe19f6c2",
			"parentId": "5c6687d65e9d882c8841f121",
			"slotId": "pocket2",
			"location": {
				"x": 0,
				"y": 0,
				"r": "Horizontal"
			},
			"upd": {
				"SpawnedInSession": true
			}
		},
		{
			"_id": "Pocket_357368",
			"_tpl": "57a349b2245977762b199ec7",
			"parentId": "5c6687d65e9d882c8841f121",
			"slotId": "pocket3",
			"location": {
				"x": 0,
				"y": 0,
				"r": "Horizontal"
			},
			"upd": {
				"SpawnedInSession": true
			}
		}
	],
	"equipment": "5c6687d65e9d882c8841f0fd",
	"stash": "5c6687d65e9d882c8841f0fc",
	"questRaidItems": "5c6687d65e9d882c8841f0fe",
	"questStashItems": "5c6687d65e9d882c8841f0ff",
	"fastPanel": {}
}