{
	"items": [
		{
			"_id": "5c6687d65e9d882c8841f0fd",
			"_tpl": "55d7217a4bdc2d86028b456d"
		},
		{
			"_id": "5c6687d65e9d882c8841f121",
			"_tpl": "557ffd194bdc2d28148b457f",
			"parentId": "5c6687d65e9d882c8841f0fd",
			"slotId": "Pockets"
		},
		{
			"_id": "5c6687d65e9d882c8841f0fc",
			"_tpl": "566abbc34bdc2d92178b4576"
		},
		{
			"_id": "5c6687d65e9d882c8841f0ff",
			"_tpl": "5963866b86f7747bfa1c4462"
		},
		{
			"_id": "5c6687d65e9d882c8841f0fe",
			"_tpl": "5963866286f7747bf429b572"
		},
		{
			"_id": "TacticalVest266959",
			"_tpl": "5c0e446786f7742013381639",
			"parentId": "5c6687d65e9d882c8841f0fd",
			"slotId": "TacticalVest",
			"upd": {
				"SpawnedInSession": true
			}
		},
		{
			"_id": "5b439b5686f77428bd137432",
			"_tpl": "5b0bbe4e5acfc40dc528a72d",
			"parentId": "5c6687d65e9d882c8841f0fd",
			"slotId": "FirstPrimaryWeapon"
		},
		{
			"_id": "5b439b5686f77428bd137433",
			"_tpl": "5b099b965acfc400186331e6",
			"parentId": "5b439b5686f77428bd137432",
			"slotId": "mod_pistol_grip",
			"upd": {
				"SpawnedInSession": true
			}
		},
		{
			"_id": "MagazineWeaponScav8803",
			"_tpl": "5b7bef1e5acfc43d82528402",
			"parentId": "5b439b5686f77428bd137432",
			"slotId": "mod_magazine",
			"upd": {
				"SpawnedInSession": true
			}
		},
		{
			"_id": "AmmoMag11951",
			"_tpl": "5e023e6e34d52a55c3304f71",
			"parentId": "MagazineWeaponScav8803",
			"slotId": "cartridges",
			"upd": {
				"SpawnedInSession": true,
				"StackObjectsCount": 10
			}
		},
		{
			"_id": "5b439b5686f77428bd137435",
			"_tpl": "5b099a9d5acfc47a8607efe7",
			"parentId": "5b439b5686f77428bd137432",
			"slotId": "mod_handguard",
			"upd": {
				"SpawnedInSession": true
			}
		},
		{
			"_id": "5b439b5686f77428bd137436",
			"_tpl": "5b099a765acfc47a8607efe3",
			"parentId": "5b439b5686f77428bd137432",
			"slotId": "mod_barrel",
			"upd": {
				"SpawnedInSession": true
			}
		},
		{
			"_id": "5b439b5686f77428bd137437",
			"_tpl": "5b099b7d5acfc400186331e4",
			"parentId": "5b439b5686f77428bd137436",
			"slotId": "mod_muzzle",
			"upd": {
				"SpawnedInSession": true
			}
		},
		{
			"_id": "5b439b5686f77428bd137438",
			"_tpl": "5b0bc22d5acfc47a8607f085",
			"parentId": "5b439b5686f77428bd137432",
			"slotId": "mod_sight_rear",
			"upd": {
				"SpawnedInSession": true
			}
		},
		{
			"_id": "5b439b5686f77428bd137439",
			"_tpl": "5b099bb25acfc400186331e8",
			"parentId": "5b439b5686f77428bd137432",
			"slotId": "mod_reciever",
			"upd": {
				"SpawnedInSession": true
			}
		},
		{
			"_id": "5b439b5686f77428bd13743a",
			"_tpl": "5b099bf25acfc4001637e683",
			"parentId": "5b439b5686f77428bd137432",
			"slotId": "mod_stock",
			"upd": {
				"SpawnedInSession": true
			}
		},
		{
			"_id": "5b439b5686f77428bd13743b",
			"_tpl": "5649be884bdc2d79388b4577",
			"parentId": "5b439b5686f77428bd13743a",
			"slotId": "mod_stock_000",
			"upd": {
				"SpawnedInSession": true
			}
		},
		{
			"_id": "5b439b5686f77428bd13743c",
			"_tpl": "56eabf3bd2720b75698b4569",
			"parentId": "5b439b5686f77428bd13743b",
			"slotId": "mod_stock_000",
			"upd": {
				"SpawnedInSession": true
			}
		},
		{
			"_id": "5b439b5686f77428bd13743d",
			"_tpl": "58d2912286f7744e27117493",
			"parentId": "5b439b5686f77428bd13743c",
			"slotId": "mod_stock",
			"upd": {
				"SpawnedInSession": true
			}
		},
		{
			"_id": "mag2Vest561189",
			"_tpl": "5b7bef1e5acfc43d82528402",
			"parentId": "TacticalVest266959",
			"slotId": "3",
			"location": {
				"x": 0,
				"y": 0,
				"r": "Horizontal"
			},
			"upd": {
				"SpawnedInSession": true
			}
		},
		{
			"_id": "AmmoMag2Vest805480",
			"_tpl": "5a6086ea4f39f99cd479502f",
			"parentId": "mag2Vest561189",
			"slotId": "cartridges",
			"upd": {
				"SpawnedInSession": true,
				"StackObjectsCount": 10
			}
		},
		{
			"_id": "mag2Vest323657",
			"_tpl": "5b7bef1e5acfc43d82528402",
			"parentId": "TacticalVest266959",
			"slotId": "3",
			"location": {
				"x": 0,
				"y": 1,
				"r": "Horizontal"
			},
			"upd": {
				"SpawnedInSession": true
			}
		},
		{
			"_id": "AmmoMag2Vest485784",
			"_tpl": "58dd3ad986f77403051cba8f",
			"parentId": "mag2Vest323657",
			"slotId": "cartridges",
			"upd": {
				"SpawnedInSession": true,
				"StackObjectsCount": 10
			}
		},
		{
			"_id": "StackAmmo54343368138",
			"_tpl": "5a6086ea4f39f99cd479502f",
			"parentId": "TacticalVest266959",
			"slotId": "5",
			"upd": {
				"SpawnedInSession": true,
				"StackObjectsCount": 32
			}
		},
		{
			"_id": "Scabbard612603",
			"_tpl": "5bffdd7e0db834001b734a1a",
			"parentId": "5c6687d65e9d882c8841f0fd",
			"slotId": "Scabbard",
			"upd": {
				"SpawnedInSession": true
			}
		},
		{
			"_id": "FaceCover56448",
			"_tpl": "572b7f1624597762ae139822",
			"parentId": "5c6687d65e9d882c8841f0fd",
			"slotId": "FaceCover",
			"upd": {
				"SpawnedInSession": true
			}
		},
		{
			"_id": "Backpack321473",
			"_tpl": "56e33634d2720bd8058b456b",
			"parentId": "5c6687d65e9d882c8841f0fd",
			"slotId": "Backpack",
			"upd": {
				"SpawnedInSession": true
			}
		},
		{
			"_id": "BP_Backpack321473_390968",
			"_tpl": "5894a51286f77426d13baf02",
			"parentId": "Backpack321473",
			"slotId": "main",
			"location": {
				"x": 0,
				"y": 0,
				"r": "Horizontal"
			},
			"upd": {
				"SpawnedInSession": true
			}
		},
		{
			"_id": "BP_Backpack321473_685942",
			"_tpl": "5c0684e50db834002a12585a",
			"parentId": "Backpack321473",
			"slotId": "main",
			"location": {
				"x": 0,
				"y": 1,
				"r": "Horizontal"
			},
			"upd": {
				"SpawnedInSession": true
			}
		},
		{
			"_id": "BP_Backpack321473_130609",
			"_tpl": "5b3f7bf05acfc433000ecf6b",
			"parentId": "Backpack321473",
			"slotId": "main",
			"location": {
				"x": 0,
				"y": 2,
				"r": "Horizontal"
			},
			"upd": {
				"SpawnedInSession": true
			}
		},
		{
			"_id": "Pocket_218848",
			"_tpl": "5780cda02459777b272ede61",
			"parentId": "5c6687d65e9d882c8841f121",
			"slotId": "pocket1",
			"location": {
				"x": 0,
				"y": 0,
				"r": "Horizontal"
			},
			"upd": {
				"SpawnedInSession": true
			}
		}
	],
	"equipment": "5c6687d65e9d882c8841f0fd",
	"stash": "5c6687d65e9d882c8841f0fc",
	"questRaidItems": "5c6687d65e9d882c8841f0fe",
	"questStashItems": "5c6687d65e9d882c8841f0ff",
	"fastPanel": {}
}