{
	"items": [
		{
			"_id": "5c6687d65e9d882c8841f0fd",
			"_tpl": "55d7217a4bdc2d86028b456d"
		},
		{
			"_id": "5c6687d65e9d882c8841f121",
			"_tpl": "557ffd194bdc2d28148b457f",
			"parentId": "5c6687d65e9d882c8841f0fd",
			"slotId": "Pockets"
		},
		{
			"_id": "5c6687d65e9d882c8841f0fc",
			"_tpl": "566abbc34bdc2d92178b4576"
		},
		{
			"_id": "5c6687d65e9d882c8841f0ff",
			"_tpl": "5963866b86f7747bfa1c4462"
		},
		{
			"_id": "5c6687d65e9d882c8841f0fe",
			"_tpl": "5963866286f7747bf429b572"
		},
		{
			"_id": "TacticalVest424953",
			"_tpl": "5df8a42886f77412640e2e75",
			"parentId": "5c6687d65e9d882c8841f0fd",
			"slotId": "TacticalVest",
			"upd": {
				"SpawnedInSession": true
			}
		},
		{
			"_id": "I081825292888443364QL9eK",
			"_tpl": "574d967124597745970e7c94",
			"parentId": "5c6687d65e9d882c8841f0fd",
			"slotId": "FirstPrimaryWeapon"
		},
		{
			"_id": "I0818252961449652734krKY",
			"_tpl": "574dad8024597745964bf05c",
			"parentId": "I081825292888443364QL9eK",
			"slotId": "mod_stock",
			"upd": {
				"SpawnedInSession": true
			}
		},
		{
			"_id": "I081825293709987055LD0E4",
			"_tpl": "574db213245977459a2f3f5d",
			"parentId": "I081825292888443364QL9eK",
			"slotId": "mod_sight_rear",
			"upd": {
				"SpawnedInSession": true
			}
		},
		{
			"_id": "MagazineWeaponScav5155",
			"_tpl": "587df3a12459772c28142567",
			"parentId": "I081825292888443364QL9eK",
			"slotId": "mod_magazine"
		},
		{
			"_id": "AmmoMag15869",
			"_tpl": "59e4d3d286f774176a36250a",
			"parentId": "MagazineWeaponScav5155",
			"slotId": "cartridges",
			"upd": {
				"StackObjectsCount": 10
			}
		},
		{
			"_id": "I081825298337229994wkM2w",
			"_tpl": "5cf67cadd7f00c065a5abab7",
			"parentId": "I081825292888443364QL9eK",
			"slotId": "mod_muzzle",
			"upd": {
				"SpawnedInSession": true
			}
		},
		{
			"_id": "I081825299814861947b35xy",
			"_tpl": "593d1fa786f7746da62d61ac",
			"parentId": "I0818252961449652734krKY",
			"slotId": "mod_mount_001",
			"upd": {
				"SpawnedInSession": true
			}
		},
		{
			"_id": "I081825295127906190KXIsZ",
			"_tpl": "5b30b0dc5acfc400153b7124",
			"parentId": "I081825299814861947b35xy",
			"slotId": "mod_scope",
			"upd": {
				"SpawnedInSession": true
			}
		},
		{
			"_id": "I081825296359873595nlYar",
			"_tpl": "5b07dd285acfc4001754240d",
			"parentId": "I081825299814861947b35xy",
			"slotId": "mod_tactical_003",
			"upd": {
				"SpawnedInSession": true
			}
		},
		{
			"_id": "I081825291625229147KY4hc",
			"_tpl": "5649ab884bdc2ded0b8b457f",
			"parentId": "I081825298337229994wkM2w",
			"slotId": "mod_muzzle",
			"upd": {
				"SpawnedInSession": true
			}
		},
		{
			"_id": "mag0Vest402449",
			"_tpl": "587df3a12459772c28142567",
			"parentId": "TacticalVest424953",
			"slotId": "1",
			"location": {
				"x": 0,
				"y": 0,
				"r": "Horizontal"
			}
		},
		{
			"_id": "AmmoMag0Vest535671",
			"_tpl": "59e4cf5286f7741778269d8a",
			"parentId": "mag0Vest402449",
			"slotId": "cartridges",
			"upd": {
				"StackObjectsCount": 10
			}
		},
		{
			"_id": "mag0Vest894691",
			"_tpl": "587df3a12459772c28142567",
			"parentId": "TacticalVest424953",
			"slotId": "1",
			"location": {
				"x": 0,
				"y": 1,
				"r": "Horizontal"
			}
		},
		{
			"_id": "AmmoMag0Vest607599",
			"_tpl": "5656d7c34bdc2d9d198b4587",
			"parentId": "mag0Vest894691",
			"slotId": "cartridges",
			"upd": {
				"StackObjectsCount": 10
			}
		},
		{
			"_id": "mag1Vest137203",
			"_tpl": "587df3a12459772c28142567",
			"parentId": "TacticalVest424953",
			"slotId": "3",
			"location": {
				"x": 0,
				"y": 0,
				"r": "Horizontal"
			}
		},
		{
			"_id": "AmmoMag1Vest13772",
			"_tpl": "5656d7c34bdc2d9d198b4587",
			"parentId": "mag1Vest137203",
			"slotId": "cartridges",
			"upd": {
				"StackObjectsCount": 10
			}
		},
		{
			"_id": "mag1Vest135950",
			"_tpl": "587df3a12459772c28142567",
			"parentId": "TacticalVest424953",
			"slotId": "3",
			"location": {
				"x": 0,
				"y": 1,
				"r": "Horizontal"
			}
		},
		{
			"_id": "AmmoMag1Vest771578",
			"_tpl": "59e0d99486f7744a32234762",
			"parentId": "mag1Vest135950",
			"slotId": "cartridges",
			"upd": {
				"StackObjectsCount": 10
			}
		},
		{
			"_id": "mag2Vest105822",
			"_tpl": "587df3a12459772c28142567",
			"parentId": "TacticalVest424953",
			"slotId": "5",
			"location": {
				"x": 0,
				"y": 1,
				"r": "Horizontal"
			}
		},
		{
			"_id": "AmmoMag2Vest144710",
			"_tpl": "59e4d24686f7741776641ac7",
			"parentId": "mag2Vest105822",
			"slotId": "cartridges",
			"upd": {
				"StackObjectsCount": 10
			}
		},
		{
			"_id": "mag4Vest491658",
			"_tpl": "587df3a12459772c28142567",
			"parentId": "TacticalVest424953",
			"slotId": "8",
			"location": {
				"x": 0,
				"y": 0,
				"r": "Horizontal"
			}
		},
		{
			"_id": "AmmoMag4Vest690768",
			"_tpl": "59e4cf5286f7741778269d8a",
			"parentId": "mag4Vest491658",
			"slotId": "cartridges",
			"upd": {
				"StackObjectsCount": 10
			}
		},
		{
			"_id": "mag5Vest623048",
			"_tpl": "587df3a12459772c28142567",
			"parentId": "TacticalVest424953",
			"slotId": "12",
			"location": {
				"x": 0,
				"y": 0,
				"r": "Horizontal"
			}
		},
		{
			"_id": "AmmoMag5Vest838966",
			"_tpl": "59e0d99486f7744a32234762",
			"parentId": "mag5Vest623048",
			"slotId": "cartridges",
			"upd": {
				"StackObjectsCount": 10
			}
		},
		{
			"_id": "Scabbard484941",
			"_tpl": "5bffdc370db834001d23eca8",
			"parentId": "5c6687d65e9d882c8841f0fd",
			"slotId": "Scabbard",
			"upd": {
				"SpawnedInSession": true
			}
		},
		{
			"_id": "Headwear292411",
			"_tpl": "5aa2b9ede5b5b000137b758b",
			"parentId": "5c6687d65e9d882c8841f0fd",
			"slotId": "Headwear",
			"upd": {
				"SpawnedInSession": true
			}
		},
		{
			"_id": "Eyewear681424",
			"_tpl": "59e770b986f7742cbd762754",
			"parentId": "5c6687d65e9d882c8841f0fd",
			"slotId": "Eyewear",
			"upd": {
				"SpawnedInSession": true
			}
		}
	],
	"equipment": "5c6687d65e9d882c8841f0fd",
	"stash": "5c6687d65e9d882c8841f0fc",
	"questRaidItems": "5c6687d65e9d882c8841f0fe",
	"questStashItems": "5c6687d65e9d882c8841f0ff",
	"fastPanel": {}
}